[{"__type__":"cc.AnimationClip","_name":"wuzhuangbwl_jiao_R_ani","_duration":1.25,"curveData":{"paths":{"jiao_L_2":{"props":{"position":[{"frame":0.7833333333333333,"value":[-25.897,-12.316,0]}],"scale":[{"frame":0.8166666666666667,"value":{"__type__":"cc.Vec2","x":1.406,"y":1.406}},{"frame":0.8666666666666667,"value":{"__type__":"cc.Vec2","x":1.2435999999999998,"y":1.2435999999999998}},{"frame":0.8833333333333333,"value":{"__type__":"cc.Vec2","x":1,"y":1}}],"opacity":[{"frame":0.7833333333333333,"value":0},{"frame":0.8166666666666667,"value":255}]}},"jiao_L_1":{"props":{"position":[{"frame":0.9166666666666666,"value":[-81.427,-68.021,0]},{"frame":0.9666666666666667,"value":[-68.81580000000001,-49.92580000000002,0]},{"frame":0.9833333333333333,"value":[-49.899,-22.783,0]}],"opacity":[{"frame":0.8833333333333333,"value":0},{"frame":0.9166666666666666,"value":255}]}},"jiao_L_3":{"props":{"position":[{"frame":1.1833333333333333,"value":[-10.255,-8.82,0]},{"frame":1.2333333333333334,"value":[2.5314000000000583,-14.574400000000026,0]},{"frame":1.25,"value":[21.711,-23.206,0]}],"opacity":[{"frame":1.15,"value":0},{"frame":1.1833333333333333,"value":255}]}}}}},[{"__type__":"cc.Prefab","_name":"wuzhuangbwl_jiao_R_ani","data":{"__id__":1}},{"__type__":"cc.Node","_name":"wuzhuangbwl_jiao_R_ani","_children":[{"__id__":2},{"__id__":3},{"__id__":4}],"_components":[{"__type__":"cc.Animation","node":{"__id__":1},"_clips":[{"__uuid__":"93kV1CWixHdaaWR4gG8v67"}]}],"_prefab":{"__type__":"cc.PrefabInfo","root":{"__id__":1},"asset":{"__id__":0},"fileId":"9bRd8fgahG65hwPhU0ut3Y"},"_color":{"__type__":"cc.Color","r":144,"g":144,"b":144},"_trs":{"__type__":"TypedArray","ctor":"Float64Array","array":[7.511,-125.208,0,0,0,0.00622205863584984,0.9999806428058156,0.93,0.93,0.93]},"_eulerAngles":{"__type__":"cc.Vec3","z":0.7129999999999992}},{"__type__":"cc.Node","_name":"jiao_L_3","_parent":{"__id__":1},"_components":[{"__type__":"cc.Sprite","node":{"__id__":2},"_materials":[{"__uuid__":"ecpdLyjvZBwrvm+cedCcQy"}],"_spriteFrame":{"__uuid__":"4b43ah2plG96jcK9tKhXSe"}}],"_prefab":{"__type__":"cc.PrefabInfo","root":{"__id__":1},"asset":{"__id__":0},"fileId":"6fiBGxvtxJhLvPv4hYoCy1"},"_color":{"__type__":"cc.Color","r":144,"g":144,"b":144},"_contentSize":{"__type__":"cc.Size","width":35,"height":34},"_trs":{"__type__":"TypedArray","ctor":"Float64Array","array":[21.711,-23.206,0,0,0,0,1,1,1,1]}},{"__type__":"cc.Node","_name":"jiao_L_2","_parent":{"__id__":1},"_components":[{"__type__":"cc.Sprite","node":{"__id__":3},"_materials":[{"__uuid__":"ecpdLyjvZBwrvm+cedCcQy"}],"_spriteFrame":{"__uuid__":"68FMx7KHBCK7HCmLg6HcvG"}}],"_prefab":{"__type__":"cc.PrefabInfo","root":{"__id__":1},"asset":{"__id__":0},"fileId":"5bXajW6PlMxLU3PkdHScch"},"_color":{"__type__":"cc.Color","r":144,"g":144,"b":144},"_contentSize":{"__type__":"cc.Size","width":99,"height":45},"_trs":{"__type__":"TypedArray","ctor":"Float64Array","array":[-25.897,-12.316,0,0,0,0,1,1,1,1]}},{"__type__":"cc.Node","_name":"jiao_L_1","_parent":{"__id__":1},"_components":[{"__type__":"cc.Sprite","node":{"__id__":4},"_materials":[{"__uuid__":"ecpdLyjvZBwrvm+cedCcQy"}],"_spriteFrame":{"__uuid__":"11sRo3SK1IFLY9/Lw9m3GX"}}],"_prefab":{"__type__":"cc.PrefabInfo","root":{"__id__":1},"asset":{"__id__":0},"fileId":"db7DQjzvdJHrLsZRGpkLuH"},"_color":{"__type__":"cc.Color","r":144,"g":144,"b":144},"_contentSize":{"__type__":"cc.Size","width":84,"height":37},"_trs":{"__type__":"TypedArray","ctor":"Float64Array","array":[-49.899,-22.783,0,0,0,0,1,1,1,1]}}]]