[{"__type__":"cc.SpriteFrame","content":{"name":"kuabu_5","texture":"133a80435","rect":[265,660,67,50],"offset":[0,0],"originalSize":[67,50],"rotated":1,"capInsets":[0,0,0,0]}},[{"__type__":"cc.Prefab","_name":"wuzhuangbwl_kuabu1_ani","data":{"__id__":1}},{"__type__":"cc.Node","_name":"wuzhuangbwl_kuabu1_ani","_children":[{"__id__":2},{"__id__":3},{"__id__":4},{"__id__":5},{"__id__":6},{"__id__":7},{"__id__":8},{"__id__":9}],"_components":[{"__type__":"cc.Animation","node":{"__id__":1},"_clips":[{"__uuid__":"57rZiD5yBEZJHpONuHVQyI"}]}],"_prefab":{"__type__":"cc.PrefabInfo","root":{"__id__":1},"asset":{"__id__":0},"fileId":"3ajvafWndJD6nGL+0b4xYF"},"_trs":{"__type__":"TypedArray","ctor":"Float64Array","array":[-16.889,1.256,0,0,0,0,1,1,1,1]}},{"__type__":"cc.Node","_name":"kuabu_8","_parent":{"__id__":1},"_components":[{"__type__":"cc.Sprite","node":{"__id__":2},"_materials":[{"__uuid__":"ecpdLyjvZBwrvm+cedCcQy"}],"_spriteFrame":{"__uuid__":"4bYuzZVApNl5OI8vlRRAlN"}}],"_prefab":{"__type__":"cc.PrefabInfo","root":{"__id__":1},"asset":{"__id__":0},"fileId":"8akS/53dpMtLNdfsYbjXDz"},"_contentSize":{"__type__":"cc.Size","width":199,"height":155},"_trs":{"__type__":"TypedArray","ctor":"Float64Array","array":[22.462,-9.107,0,0,0,0,1,1,1,1]}},{"__type__":"cc.Node","_name":"kuabu_7","_parent":{"__id__":1},"_components":[{"__type__":"cc.Sprite","node":{"__id__":3},"_materials":[{"__uuid__":"ecpdLyjvZBwrvm+cedCcQy"}],"_spriteFrame":{"__uuid__":"87susqO3ZNepTpYypgU4eD"}}],"_prefab":{"__type__":"cc.PrefabInfo","root":{"__id__":1},"asset":{"__id__":0},"fileId":"f7PAc7BFFNdLv2xTIoMoxO"},"_contentSize":{"__type__":"cc.Size","width":88,"height":62},"_trs":{"__type__":"TypedArray","ctor":"Float64Array","array":[38.855,-49.176,0,0,0,0,1,1,1,1]}},{"__type__":"cc.Node","_name":"kuabu_6","_parent":{"__id__":1},"_components":[{"__type__":"cc.Sprite","node":{"__id__":4},"_materials":[{"__uuid__":"ecpdLyjvZBwrvm+cedCcQy"}],"_spriteFrame":{"__uuid__":"f2xmPGmdRC1YJM9E/S//H9"}}],"_prefab":{"__type__":"cc.PrefabInfo","root":{"__id__":1},"asset":{"__id__":0},"fileId":"d3cNvjPSpOyZENxTpUsUu4"},"_contentSize":{"__type__":"cc.Size","width":58,"height":37},"_trs":{"__type__":"TypedArray","ctor":"Float64Array","array":[94.1,63.138,0,0,0,0,1,1,1,1]}},{"__type__":"cc.Node","_name":"kuabu_5","_parent":{"__id__":1},"_components":[{"__type__":"cc.Sprite","node":{"__id__":5},"_materials":[{"__uuid__":"ecpdLyjvZBwrvm+cedCcQy"}],"_spriteFrame":{"__uuid__":"0avl7Ih7hKJK8+FeL8pDUj"}}],"_prefab":{"__type__":"cc.PrefabInfo","root":{"__id__":1},"asset":{"__id__":0},"fileId":"87so4x171Fu7Dgmfv7hE63"},"_contentSize":{"__type__":"cc.Size","width":67,"height":50},"_trs":{"__type__":"TypedArray","ctor":"Float64Array","array":[71.03,-36.426,0,0,0,0,1,1,1,1]}},{"__type__":"cc.Node","_name":"kuabu_4","_parent":{"__id__":1},"_components":[{"__type__":"cc.Sprite","node":{"__id__":6},"_materials":[{"__uuid__":"ecpdLyjvZBwrvm+cedCcQy"}],"_spriteFrame":{"__uuid__":"fc4AVQm2NOeroF7wgmCApg"}}],"_prefab":{"__type__":"cc.PrefabInfo","root":{"__id__":1},"asset":{"__id__":0},"fileId":"af/JR7G3BBbpuCGCMdQGBN"},"_contentSize":{"__type__":"cc.Size","width":77,"height":55},"_trs":{"__type__":"TypedArray","ctor":"Float64Array","array":[17.606,-67.388,0,0,0,0,1,1,1,1]}},{"__type__":"cc.Node","_name":"kuabu_3","_parent":{"__id__":1},"_components":[{"__type__":"cc.Sprite","node":{"__id__":7},"_materials":[{"__uuid__":"ecpdLyjvZBwrvm+cedCcQy"}],"_spriteFrame":{"__uuid__":"ab7MFYBWZHj6qB4oW0rX8M"}}],"_prefab":{"__type__":"cc.PrefabInfo","root":{"__id__":1},"asset":{"__id__":0},"fileId":"afoYsAmGdLX68SwN2NfcqD"},"_contentSize":{"__type__":"cc.Size","width":95,"height":128},"_trs":{"__type__":"TypedArray","ctor":"Float64Array","array":[27.319,6.071,0,0,0,0,1,1,1,1]}},{"__type__":"cc.Node","_name":"kuabu_2","_parent":{"__id__":1},"_components":[{"__type__":"cc.Sprite","node":{"__id__":8},"_materials":[{"__uuid__":"ecpdLyjvZBwrvm+cedCcQy"}],"_spriteFrame":{"__uuid__":"d7OKUVZnxL4qR9uY6jhAhC"}}],"_prefab":{"__type__":"cc.PrefabInfo","root":{"__id__":1},"asset":{"__id__":0},"fileId":"662S/WxtVN/bG+zSaXl/jD"},"_contentSize":{"__type__":"cc.Size","width":91,"height":52},"_trs":{"__type__":"TypedArray","ctor":"Float64Array","array":[43.104,55.853,0,0,0,0,1,1,1,1]}},{"__type__":"cc.Node","_name":"kuabu_1","_parent":{"__id__":1},"_components":[{"__type__":"cc.Sprite","node":{"__id__":9},"_materials":[{"__uuid__":"ecpdLyjvZBwrvm+cedCcQy"}],"_spriteFrame":{"__uuid__":"a32kJjyrFOq4a6YvpQ3IOL"}}],"_prefab":{"__type__":"cc.PrefabInfo","root":{"__id__":1},"asset":{"__id__":0},"fileId":"26FkmH/AZA5Yrf6xF+Y5Zq"},"_contentSize":{"__type__":"cc.Size","width":98,"height":159},"_trs":{"__type__":"TypedArray","ctor":"Float64Array","array":[-33.39,16.392,0,0,0,0,1,1,1,1]}}],{"__type__":"cc.SpriteFrame","content":{"name":"kuabu_8","texture":"133a80435","rect":[3,3,199,155],"offset":[0,0],"originalSize":[199,155],"capInsets":[0,0,0,0]}},{"__type__":"cc.AnimationClip","_name":"wuzhuangbwl_kuabu1_ani","_duration":0.9333333333333333,"curveData":{"paths":{"kuabu_8":{"props":{"position":[{"frame":0,"value":[22.462,-9.107,0]}],"scale":[{"frame":0.03333333333333333,"value":{"__type__":"cc.Vec2","x":1.209,"y":1.209}},{"frame":0.11666666666666667,"value":{"__type__":"cc.Vec2","x":1.1393333333333333,"y":1.1393333333333333}},{"frame":0.13333333333333333,"value":{"__type__":"cc.Vec2","x":1,"y":1}}],"opacity":[{"frame":0,"value":0},{"frame":0.03333333333333333,"value":255}]}},"kuabu_7":{"props":{"position":[{"frame":0.5666666666666667,"value":[22.463,-17,0]},{"frame":0.6333333333333333,"value":[27.927,-27.72533333333333,0]},{"frame":0.6666666666666666,"value":[38.855,-49.176,0]}],"opacity":[{"frame":0.5333333333333333,"value":0},{"frame":0.5666666666666667,"value":255}]}},"kuabu_6":{"props":{"position":[{"frame":0.8333333333333334,"value":[48.568,45.532,0]},{"frame":0.9,"value":[63.74533333333333,51.400666666666666,0]},{"frame":0.9333333333333333,"value":[94.1,63.138,0]}],"opacity":[{"frame":0.8,"value":0},{"frame":0.8333333333333334,"value":255}]}},"kuabu_5":{"props":{"position":[{"frame":0.7,"value":[26.712,-6.678,0]},{"frame":0.7666666666666667,"value":[41.48466666666667,-16.594,0]},{"frame":0.8,"value":[71.03,-36.426,0]}],"opacity":[{"frame":0.6666666666666666,"value":0},{"frame":0.7,"value":255}]}},"kuabu_4":{"props":{"position":[{"frame":0.7,"value":[-23.07,-20.641,0]},{"frame":0.7666666666666667,"value":[-9.511333333333333,-36.22333333333333,0]},{"frame":0.8,"value":[17.606,-67.388,0]}],"opacity":[{"frame":0.6666666666666666,"value":0},{"frame":0.7,"value":255}]}},"kuabu_3":{"props":{"position":[{"frame":0.3,"value":[143.882,-0.607,0]},{"frame":0.38333333333333336,"value":[105.02766666666668,1.619,0]},{"frame":0.4,"value":[27.319,6.071,0]}],"opacity":[{"frame":0.26666666666666666,"value":0},{"frame":0.3,"value":255}]}},"kuabu_2":{"props":{"position":[{"frame":0.43333333333333335,"value":[149.346,63.138,0]},{"frame":0.5166666666666667,"value":[113.932,60.709666666666664,0]},{"frame":0.5333333333333333,"value":[43.104,55.853,0]}],"opacity":[{"frame":0.4,"value":0},{"frame":0.43333333333333335,"value":255}]}},"kuabu_1":{"props":{"position":[{"frame":0.16666666666666666,"value":[-65.566,72.852,0]},{"frame":0.25,"value":[-54.84066666666667,54.032000000000004,0]},{"frame":0.26666666666666666,"value":[-33.39,16.392,0]}],"opacity":[{"frame":0.13333333333333333,"value":0},{"frame":0.16666666666666666,"value":255}]}}}}},{"__type__":"cc.SpriteFrame","content":{"name":"kuabu_7","texture":"133a80435","rect":[335,353,88,62],"offset":[0,0],"originalSize":[88,62],"rotated":1,"capInsets":[0,0,0,0]}},{"__type__":"cc.SpriteFrame","content":{"name":"kuabu_1","texture":"133a80435","rect":[403,294,98,158],"offset":[0,-0.5],"originalSize":[98,159],"capInsets":[0,0,0,0]}},{"__type__":"cc.SpriteFrame","content":{"name":"kuabu_3","texture":"133a80435","rect":[3,292,95,128],"offset":[0,0],"originalSize":[95,128],"rotated":1,"capInsets":[0,0,0,0]}},{"__type__":"cc.SpriteFrame","content":{"name":"kuabu_2","texture":"133a80435","rect":[205,540,91,52],"offset":[0,0],"originalSize":[91,52],"capInsets":[0,0,0,0]}},{"__type__":"cc.SpriteFrame","content":{"name":"kuabu_6","texture":"133a80435","rect":[196,598,58,37],"offset":[0,0],"originalSize":[58,37],"rotated":1,"capInsets":[0,0,0,0]}},{"__type__":"cc.SpriteFrame","content":{"name":"kuabu_4","texture":"133a80435","rect":[338,729,77,55],"offset":[0,0],"originalSize":[77,55],"rotated":1,"capInsets":[0,0,0,0]}}]